pyamsi
