Metadata-Version: 2.1
Name: pyamsi
Version: 1.11
Summary: Access windows anitmalware interface using python
Home-page: https://github.com/Tomiwa-Ot/py-amsi
Author: Olorunfemi-Ojo Tomiwa
Author-email: ot.server1@outlook.com
License: MIT
Keywords: amsi,python-amsi,pyamsi
Platform: UNKNOWN
License-File: LICENSE
